hdl_registers/__init__.py
hdl_registers/about.py
hdl_registers/conftest.py
hdl_registers/py.typed
hdl_registers/register.py
hdl_registers/register_array.py
hdl_registers/register_list.py
hdl_registers/register_mode.py
hdl_registers/register_modes.py
hdl_registers/requirements.txt
hdl_registers/requirements_develop.txt
hdl_registers/constant/__init__.py
hdl_registers/constant/bit_vector_constant.py
hdl_registers/constant/boolean_constant.py
hdl_registers/constant/constant.py
hdl_registers/constant/float_constant.py
hdl_registers/constant/integer_constant.py
hdl_registers/constant/string_constant.py
hdl_registers/constant/test/__init__.py
hdl_registers/constant/test/test_bit_vector_constant.py
hdl_registers/constant/test/test_boolean_constant.py
hdl_registers/constant/test/test_float_constant.py
hdl_registers/constant/test/test_integer_constant.py
hdl_registers/constant/test/test_string_constant.py
hdl_registers/field/__init__.py
hdl_registers/field/bit.py
hdl_registers/field/bit_vector.py
hdl_registers/field/enumeration.py
hdl_registers/field/integer.py
hdl_registers/field/numerical_interpretation.py
hdl_registers/field/register_field.py
hdl_registers/field/test/__init__.py
hdl_registers/field/test/test_bit.py
hdl_registers/field/test/test_bit_vector.py
hdl_registers/field/test/test_enumeration.py
hdl_registers/field/test/test_integer.py
hdl_registers/field/test/test_numerical_interpretation.py
hdl_registers/generator/__init__.py
hdl_registers/generator/register_code_generator.py
hdl_registers/generator/register_code_generator_helpers.py
hdl_registers/generator/reserved_keywords.py
hdl_registers/generator/c/__init__.py
hdl_registers/generator/c/header.py
hdl_registers/generator/c/reserved_keywords.py
hdl_registers/generator/cpp/__init__.py
hdl_registers/generator/cpp/cpp_generator_common.py
hdl_registers/generator/cpp/header.py
hdl_registers/generator/cpp/implementation.py
hdl_registers/generator/cpp/interface.py
hdl_registers/generator/cpp/reserved_keywords.py
hdl_registers-8.1.0.dist-info/METADATA
hdl_registers-8.1.0.dist-info/WHEEL
hdl_registers-8.1.0.dist-info/top_level.txt
hdl_registers-8.1.0.dist-info/RECORD
