Metadata-Version: 2.4
Name: hdl_registers
Version: 8.1.0
Summary: An open-source HDL register interface code generator fast enough to run in real time
Author: Lukas Vik
Author-email: 10241915+LukasVik@users.noreply.github.com
License: BSD 3-Clause License
Project-URL: Homepage, https://hdl-registers.com
Project-URL: Documentation, https://hdl-registers.com
Project-URL: Changelog, https://hdl-registers.com/rst/about/release_notes.html
Project-URL: Source, https://github.com/hdl-registers/hdl-registers
Project-URL: Issues, https://github.com/hdl-registers/hdl-registers/issues
Keywords: python,c,html,asic,generator,fpga,cplusplus,register,vhdl,eda,rtl,csr,axi,axi-lite,register-interface
Classifier: Development Status :: 5 - Production/Stable
Classifier: Intended Audience :: Developers
Classifier: Intended Audience :: Education
Classifier: Intended Audience :: Information Technology
Classifier: License :: OSI Approved :: BSD License
Classifier: Natural Language :: English
Classifier: Operating System :: MacOS :: MacOS X
Classifier: Operating System :: Microsoft :: Windows
Classifier: Operating System :: OS Independent
Classifier: Operating System :: POSIX :: Linux
Classifier: Topic :: Scientific/Engineering :: Electronic Design Automation (EDA)
Classifier: Topic :: Scientific/Engineering
Classifier: Topic :: Software Development :: Testing
Classifier: Topic :: Software Development
Requires-Python: >=3.10
Requires-Dist: black
Requires-Dist: docutils
Requires-Dist: GitPython
Requires-Dist: peakrdl-regblock<2.0.0,>=1.0.0
Requires-Dist: PyYAML
Requires-Dist: rtoml
Requires-Dist: termcolor
Requires-Dist: tomli-w
Requires-Dist: tsfpga>=13.2.0
Provides-Extra: develop
Requires-Dist: GitPython; extra == "develop"
Requires-Dist: packaging; extra == "develop"
Requires-Dist: pybadges; extra == "develop"
Requires-Dist: pycairo; extra == "develop"
Requires-Dist: PyGObject; extra == "develop"
Requires-Dist: pytest; extra == "develop"
Requires-Dist: pytest-cov; extra == "develop"
Requires-Dist: pytest-xdist; extra == "develop"
Requires-Dist: PyYAML; extra == "develop"
Requires-Dist: requests; extra == "develop"
Requires-Dist: ruff; extra == "develop"
Requires-Dist: setuptools; extra == "develop"
Requires-Dist: sphinx; extra == "develop"
Requires-Dist: sphinx_sitemap; extra == "develop"
Requires-Dist: sphinx-rtd-theme; extra == "develop"
Requires-Dist: sphinx-toolbox; extra == "develop"
Requires-Dist: sphinxcontrib-wavedrom; extra == "develop"
Requires-Dist: sphinxext-opengraph; extra == "develop"
Requires-Dist: twine; extra == "develop"
Requires-Dist: vunit_hdl; extra == "develop"
Dynamic: author
Dynamic: author-email
Dynamic: classifier
Dynamic: description
Dynamic: description-content-type
Dynamic: keywords
Dynamic: license
Dynamic: project-url
Dynamic: provides-extra
Dynamic: requires-dist
Dynamic: requires-python
Dynamic: summary
